pypolydim-2.0.7.dist-info/RECORD
pypolydim-2.0.7.dist-info/WHEEL
pypolydim-2.0.7.dist-info/METADATA
pypolydim-2.0.7.dist-info/licenses/LICENSE
pypolydim/export_vtk_utilities.py
pypolydim/__init__.py
pypolydim/assembler_utilities.py
pypolydim/pypolydim.cpython-311-darwin.so
pypolydim/vtk_utilities.py
pypolydim/pypolydim.pyi
