Metadata-Version: 2.2
Name: pypolydim
Version: 2.0.7
Summary: Bindings Python for PolyDiM&GeDiM based on pybind11
Keywords: vem,fem,mesh,dfn,adaptativity,geometry,voronoi,tetgen,triangle
Author-Email: Gioana Teora <gioana.teora@polito.it>, Fabio Vicini <fabio.vicini@polito.it>
Maintainer-Email: Gioana Teora <gioana.teora@polito.it>
License: GPL
Classifier: Programming Language :: Python :: 3
Classifier: Programming Language :: C++
Classifier: License :: OSI Approved :: GNU General Public License v3 (GPLv3)
Classifier: Operating System :: POSIX :: Linux
Classifier: Operating System :: MacOS
Project-URL: Homepage, https://www.polydim.it/
Project-URL: Repository, https://github.com/AURION-Polito/PolyDiM/
Project-URL: Documentation, https://docs.polydim.it/
Project-URL: Issues, https://github.com/AURION-Polito/PolyDiM/issues
Requires-Python: >=3.11
